<?xml version="1.0" encoding="UTF-8"?>

<xwikidoc reference="BookTools.Code.ConfigurationClass" locale="">
  <web>BookTools.Code</web>
  <name>ConfigurationClass</name>
  <language/>
  <defaultLanguage/>
  <translation>0</translation>
  <parent>BookTools.Code.WebHome</parent>
  <creator>xwiki:XWiki.Admin</creator>
  <author>xwiki:XWiki.Admin</author>
  <customClass/>
  <contentAuthor>xwiki:XWiki.Admin</contentAuthor>
  <creationDate>1467208771000</creationDate>
  <date>1472314970000</date>
  <contentUpdateDate>1471863202000</contentUpdateDate>
  <version>1.1</version>
  <title/>
  <defaultTemplate/>
  <validationScript/>
  <comment/>
  <minorEdit>false</minorEdit>
  <syntaxId>xwiki/2.1</syntaxId>
  <hidden>true</hidden>
  <class>
    <name>BookTools.Code.ConfigurationClass</name>
    <customClass/>
    <customMapping/>
    <defaultViewSheet/>
    <defaultEditSheet/>
    <defaultWeb/>
    <nameField/>
    <validationScript/>
    <attachmentTranslations>
      <cache>0</cache>
      <classname>XWiki.TranslationDocumentClass</classname>
      <customDisplay/>
      <disabled>0</disabled>
      <displayType>select</displayType>
      <idField/>
      <multiSelect>1</multiSelect>
      <name>attachmentTranslations</name>
      <number>3</number>
      <picker>0</picker>
      <prettyName>attachmentTranslations</prettyName>
      <relationalStorage>0</relationalStorage>
      <separator>,  </separator>
      <separators>,</separators>
      <size>5</size>
      <sort>none</sort>
      <sql/>
      <unmodifiable>0</unmodifiable>
      <validationMessage/>
      <validationRegExp/>
      <valueField/>
      <classType>com.xpn.xwiki.objects.classes.PageClass</classType>
    </attachmentTranslations>
    <entryStyle>
      <customDisplay/>
      <disabled>0</disabled>
      <editor>PureText</editor>
      <name>entryStyle</name>
      <number>5</number>
      <picker>0</picker>
      <prettyName>entryStyle</prettyName>
      <rows>10</rows>
      <size>120</size>
      <unmodifiable>0</unmodifiable>
      <validationMessage/>
      <validationRegExp/>
      <classType>com.xpn.xwiki.objects.classes.TextAreaClass</classType>
    </entryStyle>
    <extraSources>
      <cache>0</cache>
      <classname/>
      <customDisplay/>
      <disabled>0</disabled>
      <displayType>input</displayType>
      <idField/>
      <multiSelect>1</multiSelect>
      <name>extraSources</name>
      <number>5</number>
      <picker>0</picker>
      <prettyName>extraSources</prettyName>
      <relationalStorage>0</relationalStorage>
      <separator>,</separator>
      <separators>,</separators>
      <size>80</size>
      <sort>id</sort>
      <sql/>
      <unmodifiable>0</unmodifiable>
      <validationMessage/>
      <validationRegExp/>
      <valueField/>
      <classType>com.xpn.xwiki.objects.classes.DBListClass</classType>
    </extraSources>
    <scope>
      <customDisplay/>
      <disabled>0</disabled>
      <name>scope</name>
      <number>1</number>
      <picker>0</picker>
      <prettyName>scope</prettyName>
      <size>30</size>
      <unmodifiable>0</unmodifiable>
      <validationMessage/>
      <validationRegExp/>
      <classType>com.xpn.xwiki.objects.classes.StringClass</classType>
    </scope>
    <style>
      <customDisplay/>
      <disabled>0</disabled>
      <editor>PureText</editor>
      <name>style</name>
      <number>4</number>
      <picker>0</picker>
      <prettyName>style</prettyName>
      <rows>10</rows>
      <size>120</size>
      <unmodifiable>0</unmodifiable>
      <validationMessage/>
      <validationRegExp/>
      <classType>com.xpn.xwiki.objects.classes.TextAreaClass</classType>
    </style>
  </class>
  <object>
    <class>
      <name>XWiki.ClassSheetBinding</name>
      <customClass/>
      <customMapping/>
      <defaultViewSheet/>
      <defaultEditSheet/>
      <defaultWeb/>
      <nameField/>
      <validationScript/>
      <sheet>
        <customDisplay/>
        <disabled>0</disabled>
        <name>sheet</name>
        <number>1</number>
        <picker>0</picker>
        <prettyName>Sheet</prettyName>
        <size>30</size>
        <unmodifiable>0</unmodifiable>
        <validationMessage/>
        <validationRegExp/>
        <classType>com.xpn.xwiki.objects.classes.StringClass</classType>
      </sheet>
    </class>
    <name>BookTools.Code.ConfigurationClass</name>
    <number>0</number>
    <className>XWiki.ClassSheetBinding</className>
    <guid>5fa8d78c-459e-4472-bdb4-8f540478393e</guid>
    <property>
      <sheet>ConfigurationSheet</sheet>
    </property>
  </object>
  <object>
    <class>
      <name>XWiki.DocumentSheetBinding</name>
      <customClass/>
      <customMapping/>
      <defaultViewSheet/>
      <defaultEditSheet/>
      <defaultWeb/>
      <nameField/>
      <validationScript/>
      <sheet>
        <customDisplay/>
        <disabled>0</disabled>
        <name>sheet</name>
        <number>1</number>
        <picker>0</picker>
        <prettyName>Sheet</prettyName>
        <size>30</size>
        <unmodifiable>0</unmodifiable>
        <validationMessage/>
        <validationRegExp/>
        <classType>com.xpn.xwiki.objects.classes.StringClass</classType>
      </sheet>
    </class>
    <name>BookTools.Code.ConfigurationClass</name>
    <number>0</number>
    <className>XWiki.DocumentSheetBinding</className>
    <guid>dea904fb-f2f4-4367-b0d5-cfdebba833c8</guid>
    <property>
      <sheet>XWiki.ClassSheet</sheet>
    </property>
  </object>
  <content/>
</xwikidoc>
